graiax_bbot/__main__.py
graiax_bbot/bot.py
graiax_bbot/cli/__init__.py
graiax_bbot/cli/bot.py
graiax_bbot/core/__init__.py
graiax_bbot/core/announcement.py
graiax_bbot/core/bot_config.py
graiax_bbot/core/context.py
graiax_bbot/core/control.py
graiax_bbot/core/data.py
graiax_bbot/core/group_config.py
graiax_bbot/core/log.py
graiax_bbot/core/subgroup_config.py
graiax_bbot/function/__init__.py
graiax_bbot/function/command/add_talk.py
graiax_bbot/function/command/admin/add.py
graiax_bbot/function/command/admin/remove.py
graiax_bbot/function/command/announcement.py
graiax_bbot/function/command/configure/atall.py
graiax_bbot/function/command/configure/nick.py
graiax_bbot/function/command/init.py
graiax_bbot/function/command/menu/__init__.py
graiax_bbot/function/command/quit_group.py
graiax_bbot/function/command/status.py
graiax_bbot/function/command/subgroup/add.py
graiax_bbot/function/command/subgroup/add_up.py
graiax_bbot/function/command/subgroup/get_subgroup.py
graiax_bbot/function/command/subgroup/remove.py
graiax_bbot/function/command/subgroup/remove_up.py
graiax_bbot/function/command/up/get_subscribe.py
graiax_bbot/function/command/up/subscribe.py
graiax_bbot/function/command/up/unsubscribe.py
graiax_bbot/function/command/video_resolve.py
graiax_bbot/function/command/vip/add.py
graiax_bbot/function/command/vip/remove.py
graiax_bbot/function/command/vive_dynamic.py
graiax_bbot/function/command/web_auth.py
graiax_bbot/function/command/whitelist/add.py
graiax_bbot/function/command/whitelist/close.py
graiax_bbot/function/command/whitelist/open.py
graiax_bbot/function/command/whitelist/remove.py
graiax_bbot/function/event/bot_launch.py
graiax_bbot/function/event/exception.py
graiax_bbot/function/event/invited_join_group.py
graiax_bbot/function/event/join_group.py
graiax_bbot/function/event/leave_group.py
graiax_bbot/function/event/mute.py
graiax_bbot/function/event/new_friend.py
graiax_bbot/function/event/offline.py
graiax_bbot/function/event/prem_change.py
graiax_bbot-1.2.0b5.dist-info/WHEEL
graiax_bbot-1.2.0b5.dist-info/LICENSE
graiax_bbot-1.2.0b5.dist-info/METADATA
graiax_bbot-1.2.0b5.dist-info/entry_points.txt
graiax_bbot-1.2.0b5.dist-info/RECORD
