Metadata-Version: 2.1
Name: graiax-bbot
Version: 1.2.0b5
Summary: 一个用于 QQ 群内高效推送哔哩哔哩 UP 动态及直播的机器人
Home-page: https://github.com/djkcyl/BBot-Graia
License: AGPL3.0
Keywords: graia,graiax,bilibili,qqbot,grpc,playwright,fastapi,bot
Author: djkcyl
Author-email: cyl@cyllive.cn
Requires-Python: >=3.9,<4.0
Classifier: License :: Other/Proprietary License
Classifier: Programming Language :: Python :: 3
Classifier: Programming Language :: Python :: 3.9
Classifier: Programming Language :: Python :: 3.10
Classifier: Programming Language :: Python :: 3.11
Requires-Dist: Pillow (>=9.3.0,<10.0.0)
Requires-Dist: bilireq (>=0.2.3,<0.3.0)
Requires-Dist: fastapi (>=0.88.0,<0.89.0)
Requires-Dist: graia-ariadne[standard] (>=0.10.3,<0.11.0)
Requires-Dist: graiax-playwright (>=0.2.1,<0.3.0)
Requires-Dist: passlib[bcrypt] (>=1.7.4,<2.0.0)
Requires-Dist: peewee (>=3.15.4,<4.0.0)
Requires-Dist: pillow (>=9.4.0,<10.0.0)
Requires-Dist: psutil (>=5.9.4,<6.0.0)
Requires-Dist: python-jose[cryptography] (>=3.3.0,<4.0.0)
Requires-Dist: python-multipart (>=0.0.5,<0.0.6)
Requires-Dist: pyyaml (>=6.0,<7.0)
Requires-Dist: qrcode (>=7.3.1,<8.0.0)
Requires-Dist: sentry-sdk (>=1.12.1,<2.0.0)
Requires-Dist: uvicorn (>=0.19.0,<0.20.0)
Requires-Dist: websockets (>=10.4,<11.0)
Project-URL: Documentation, https://github.com/djkcyl/BBot-Graia/blob/master/readme.md
Project-URL: Repository, https://github.com/djkcyl/BBot-Graia/tree/master/graiax-bbot
